{
  "fetched_at": "2025-05-27T14:27:06.623Z",
  "data": [
    {
      "title": "ین ژاپن (100 ین) ",
      "dp": 7314.82,
      "type": "high",
      "h": "578210",
      "l": "574590",
      "p": "575390",
      "t": "۱۷:۵۴:۰۰",
      "id": 137210
    },
    {
      "title": "دینار عراق ",
      "dp": 2.87,
      "type": "high",
      "h": "575",
      "l": "560",
      "p": "574",
      "t": "۱۷:۳۹:۲۳",
      "id": 137217
    },
    {
      "title": "لاری گرجستان ",
      "dp": 0.66,
      "type": "high",
      "h": "304200",
      "l": "301800",
      "p": "303900",
      "t": "۱۷:۵۴:۰۱",
      "id": 137235
    },
    {
      "title": "آنتیل گیلدر هلند",
      "dp": 0.62,
      "type": "high",
      "h": "474900",
      "l": "471500",
      "p": "474400",
      "t": "۱۷:۵۴:۰۲",
      "id": 520875
    },
    {
      "title": "دلار",
      "dp": 0.61,
      "type": "high",
      "h": "828000",
      "l": "822100",
      "p": "827500",
      "t": "۱۷:۵۴:۰۲",
      "id": 137203
    },
    {
      "title": "دینار بحرین ",
      "dp": 0.6,
      "type": "high",
      "h": "2197400",
      "l": "2181200",
      "p": "2195300",
      "t": "۱۷:۵۴:۰۱",
      "id": 137230
    },
    {
      "title": "روبل روسیه ",
      "dp": 0.58,
      "type": "low",
      "h": "10430",
      "l": "10290",
      "p": "10300",
      "t": "۱۷:۵۴:۰۰",
      "id": 137214
    },
    {
      "title": "ریال عمان ",
      "dp": 0.58,
      "type": "high",
      "h": "2151700",
      "l": "2135800",
      "p": "2149100",
      "t": "۱۷:۵۴:۰۰",
      "id": 137215
    },
    {
      "title": "منات آذربایجان ",
      "dp": 0.58,
      "type": "high",
      "h": "488600",
      "l": "485100",
      "p": "488100",
      "t": "۱۷:۵۴:۰۱",
      "id": 137219
    },
    {
      "title": "درهم امارات ",
      "dp": 0.56,
      "type": "high",
      "h": "226500",
      "l": "224900",
      "p": "226280",
      "t": "۱۷:۵۴:۰۰",
      "id": 137206
    },
    {
      "title": "دینار کویت ",
      "dp": 0.54,
      "type": "high",
      "h": "2705700",
      "l": "2687300",
      "p": "2703000",
      "t": "۱۷:۵۴:۰۰",
      "id": 137212
    },
    {
      "title": "پوند انگلیس",
      "dp": 0.5,
      "type": "high",
      "h": "1123300",
      "l": "1113100",
      "p": "1121200",
      "t": "۱۷:۵۴:۰۰",
      "id": 137207
    },
    {
      "title": "هریونیا اوکراین",
      "dp": 0.5,
      "type": "high",
      "h": "20000",
      "l": "20000",
      "p": "20000",
      "t": "۱۱:۰۴:۳۱",
      "id": 520843
    },
    {
      "title": "لیر ترکیه ",
      "dp": 0.47,
      "type": "high",
      "h": "21300",
      "l": "21100",
      "p": "21200",
      "t": "۱۷:۳۰:۵۲",
      "id": 137225
    },
    {
      "title": "یوان چین ",
      "dp": 0.44,
      "type": "high",
      "h": "115100",
      "l": "114400",
      "p": "115000",
      "t": "۱۷:۵۳:۵۴",
      "id": 137222
    },
    {
      "title": "روپیه هند ",
      "dp": 0.41,
      "type": "high",
      "h": "9720",
      "l": "9640",
      "p": "9710",
      "t": "۱۷:۴۵:۴۹",
      "id": 137228
    },
    {
      "title": "دلار کانادا ",
      "dp": 0.38,
      "type": "high",
      "h": "601900",
      "l": "597800",
      "p": "601300",
      "t": "۱۷:۵۴:۰۱",
      "id": 137221
    },
    {
      "title": "یورو",
      "dp": 0.36,
      "type": "high",
      "h": "942000",
      "l": "933000",
      "p": "939500",
      "t": "۱۷:۵۴:۰۰",
      "id": 137205
    },
    {
      "title": "ریال قطر ",
      "dp": 0.34,
      "type": "high",
      "h": "236100",
      "l": "234400",
      "p": "234900",
      "t": "۱۷:۵۴:۰۱",
      "id": 137231
    },
    {
      "title": "زلوتی لهستان",
      "dp": 0.27,
      "type": "high",
      "h": "222100",
      "l": "219900",
      "p": "221500",
      "t": "۱۷:۵۴:۰۲",
      "id": 520837
    },
    {
      "title": "افغانی ",
      "dp": 0.25,
      "type": "low",
      "h": "12060",
      "l": "11870",
      "p": "11930",
      "t": "۱۷:۵۳:۵۴",
      "id": 137218
    },
    {
      "title": "روپیه پاکستان ",
      "dp": 0.24,
      "type": "high",
      "h": "2955",
      "l": "2934",
      "p": "2938",
      "t": "۱۷:۵۴:۰۱",
      "id": 137229
    },
    {
      "title": "کرون سوئد ",
      "dp": 0.23,
      "type": "low",
      "h": "86800",
      "l": "86000",
      "p": "86200",
      "t": "۱۷:۵۲:۲۲",
      "id": 137208
    },
    {
      "title": "درهم مراکش",
      "dp": 0.22,
      "type": "high",
      "h": "89900",
      "l": "89300",
      "p": "89700",
      "t": "۱۷:۴۵:۵۰",
      "id": 520793
    },
    {
      "title": "دلار استرالیا ",
      "dp": 0.11,
      "type": "low",
      "h": "534700",
      "l": "530500",
      "p": "533600",
      "t": "۱۷:۵۴:۰۱",
      "id": 137220
    },
    {
      "title": "درام ارمنستان ",
      "dp": 0,
      "type": "",
      "h": "2310",
      "l": "2150",
      "p": "2150",
      "t": "۱۷:۳۹:۰۹",
      "id": 137234
    },
    {
      "title": "پوند لبنان",
      "dp": 0,
      "type": "",
      "h": "10",
      "l": "10",
      "p": "10",
      "t": "۲۲ مرداد",
      "id": 520782
    },
    {
      "title": "وون کره جنوبی",
      "dp": 0,
      "type": "",
      "h": "610",
      "l": "600",
      "p": "600",
      "t": "۴ خرداد",
      "id": 520862
    }
  ]
}