{
  "fetched_at": "2025-05-31T16:21:37.977Z",
  "data": [
    {
      "title": "افغانی ",
      "dp": 1.51,
      "type": "high",
      "h": "12130",
      "l": "11950",
      "p": "12080",
      "t": "۱۹:۵۰:۴۶",
      "id": 137218
    },
    {
      "title": "روبل روسیه ",
      "dp": 1.42,
      "type": "high",
      "h": "10720",
      "l": "10660",
      "p": "10680",
      "t": "۱۹:۲۰:۴۲",
      "id": 137214
    },
    {
      "title": "هریونیا اوکراین",
      "dp": 1.01,
      "type": "high",
      "h": "20100",
      "l": "20000",
      "p": "20100",
      "t": "۱۹:۲۰:۴۹",
      "id": 520843
    },
    {
      "title": "درام ارمنستان ",
      "dp": 0.93,
      "type": "high",
      "h": "2160",
      "l": "2150",
      "p": "2160",
      "t": "۱۹:۲۰:۴۴",
      "id": 137234
    },
    {
      "title": "دلار کانادا ",
      "dp": 0.92,
      "type": "high",
      "h": "604800",
      "l": "601300",
      "p": "602300",
      "t": "۱۹:۴۹:۳۶",
      "id": 137221
    },
    {
      "title": "ین ژاپن (100 ین) ",
      "dp": 0.81,
      "type": "high",
      "h": "578840",
      "l": "575500",
      "p": "576750",
      "t": "۱۹:۵۰:۳۶",
      "id": 137210
    },
    {
      "title": "دینار عراق ",
      "dp": 0.7,
      "type": "high",
      "h": "577",
      "l": "573",
      "p": "574",
      "t": "۱۹:۴۹:۴۴",
      "id": 137217
    },
    {
      "title": "روپیه پاکستان ",
      "dp": 0.68,
      "type": "high",
      "h": "2963",
      "l": "2945",
      "p": "2951",
      "t": "۱۹:۵۰:۲۶",
      "id": 137229
    },
    {
      "title": "ریال قطر ",
      "dp": 0.64,
      "type": "high",
      "h": "236600",
      "l": "235300",
      "p": "235700",
      "t": "۱۹:۴۹:۳۷",
      "id": 137231
    },
    {
      "title": "لاری گرجستان ",
      "dp": 0.6,
      "type": "high",
      "h": "305400",
      "l": "303700",
      "p": "304200",
      "t": "۱۹:۴۹:۳۷",
      "id": 137235
    },
    {
      "title": "ریال عمان ",
      "dp": 0.58,
      "type": "high",
      "h": "2158200",
      "l": "2145800",
      "p": "2150400",
      "t": "۱۹:۵۰:۳۸",
      "id": 137215
    },
    {
      "title": "دلار",
      "dp": 0.57,
      "type": "high",
      "h": "830500",
      "l": "825950",
      "p": "827350",
      "t": "۱۹:۵۱:۰۸",
      "id": 137203
    },
    {
      "title": "درهم مراکش",
      "dp": 0.56,
      "type": "high",
      "h": "90100",
      "l": "89600",
      "p": "89800",
      "t": "۱۹:۲۰:۴۶",
      "id": 520793
    },
    {
      "title": "آنتیل گیلدر هلند",
      "dp": 0.55,
      "type": "high",
      "h": "476300",
      "l": "473500",
      "p": "474400",
      "t": "۱۹:۵۰:۲۹",
      "id": 520875
    },
    {
      "title": "دینار کویت ",
      "dp": 0.54,
      "type": "high",
      "h": "2711200",
      "l": "2695500",
      "p": "2700100",
      "t": "۱۹:۵۰:۳۵",
      "id": 137212
    },
    {
      "title": "منات آذربایجان ",
      "dp": 0.54,
      "type": "high",
      "h": "490100",
      "l": "487300",
      "p": "488100",
      "t": "۱۹:۴۹:۳۵",
      "id": 137219
    },
    {
      "title": "دینار بحرین ",
      "dp": 0.54,
      "type": "high",
      "h": "2204000",
      "l": "2191300",
      "p": "2195100",
      "t": "۱۹:۵۰:۲۶",
      "id": 137230
    },
    {
      "title": "درهم امارات ",
      "dp": 0.53,
      "type": "high",
      "h": "227180",
      "l": "225880",
      "p": "226260",
      "t": "۱۹:۵۰:۳۴",
      "id": 137206
    },
    {
      "title": "یورو",
      "dp": 0.52,
      "type": "high",
      "h": "942800",
      "l": "937300",
      "p": "939000",
      "t": "۱۹:۵۰:۲۵",
      "id": 137205
    },
    {
      "title": "لیر ترکیه ",
      "dp": 0.48,
      "type": "low",
      "h": "21100",
      "l": "21000",
      "p": "21000",
      "t": "۱۶:۰۶:۳۷",
      "id": 137225
    },
    {
      "title": "کرون سوئد ",
      "dp": 0.35,
      "type": "high",
      "h": "86700",
      "l": "86200",
      "p": "86300",
      "t": "۱۹:۴۹:۳۴",
      "id": 137208
    },
    {
      "title": "یوان چین ",
      "dp": 0.35,
      "type": "high",
      "h": "115400",
      "l": "114700",
      "p": "114900",
      "t": "۱۹:۴۹:۳۶",
      "id": 137222
    },
    {
      "title": "روپیه هند ",
      "dp": 0.31,
      "type": "high",
      "h": "9720",
      "l": "9670",
      "p": "9680",
      "t": "۱۹:۴۹:۳۶",
      "id": 137228
    },
    {
      "title": "پوند انگلیس",
      "dp": 0.18,
      "type": "high",
      "h": "1117500",
      "l": "1111000",
      "p": "1113000",
      "t": "۱۹:۵۰:۲۵",
      "id": 137207
    },
    {
      "title": "زلوتی لهستان",
      "dp": 0.18,
      "type": "high",
      "h": "222000",
      "l": "220800",
      "p": "221100",
      "t": "۱۹:۴۹:۴۲",
      "id": 520837
    },
    {
      "title": "دلار استرالیا ",
      "dp": 0.09,
      "type": "high",
      "h": "534000",
      "l": "530900",
      "p": "531800",
      "t": "۱۹:۴۹:۳۵",
      "id": 137220
    },
    {
      "title": "پوند لبنان",
      "dp": 0,
      "type": "",
      "h": "10",
      "l": "10",
      "p": "10",
      "t": "۲۲ مرداد",
      "id": 520782
    },
    {
      "title": "وون کره جنوبی",
      "dp": 0,
      "type": "",
      "h": "610",
      "l": "600",
      "p": "600",
      "t": "۷ خرداد",
      "id": 520862
    }
  ]
}