{
  "fetched_at": "2025-05-31T09:24:30.927Z",
  "data": [
    {
      "title": "طلای 18 عیار / 750",
      "dp": 0.28,
      "type": "high",
      "h": "65139000",
      "l": "64578000",
      "p": "64580000",
      "t": "۱۲:۵۱:۱۷",
      "id": 137121
    },
    {
      "title": "طلای ۲۴ عیار",
      "dp": 0.28,
      "type": "high",
      "h": "86851000",
      "l": "86103000",
      "p": "86106000",
      "t": "۱۲:۵۱:۱۷",
      "id": 137122
    },
    {
      "title": "آبشده بنکداری ",
      "dp": 0.28,
      "type": "high",
      "h": "282200000",
      "l": "279770000",
      "p": "279780000",
      "t": "۱۲:۵۱:۱۶",
      "id": 137147
    },
    {
      "title": "طلای 18 عیار / 740",
      "dp": 0.28,
      "type": "high",
      "h": "64270000",
      "l": "63717000",
      "p": "63719000",
      "t": "۱۲:۵۱:۱۷",
      "id": 391292
    },
    {
      "title": "آبشده کمتر از کیلو ",
      "dp": 0.28,
      "type": "high",
      "h": "282250000",
      "l": "279820000",
      "p": "279830000",
      "t": "۱۲:۵۱:۱۶",
      "id": 391294
    },
    {
      "title": "طلای دست دوم",
      "dp": 0.28,
      "type": "high",
      "h": "64270280",
      "l": "63716760",
      "p": "63719030",
      "t": "۱۲:۵۱:۱۷",
      "id": 391295
    },
    {
      "title": "مثقال طلا ",
      "dp": 0.27,
      "type": "high",
      "h": "282150000",
      "l": "279610000",
      "p": "279750000",
      "t": "۱۲:۵۱:۲۴",
      "id": 137120
    },
    {
      "title": "مثقال / بدون حباب",
      "dp": 0.2,
      "type": "low",
      "h": "285403000",
      "l": "284424000",
      "p": "284578000",
      "t": "۱۲:۵۰:۳۸",
      "id": 137148
    }
  ]
}