{
  "fetched_at": "2025-06-08T15:13:00.775Z",
  "data": [
    {
      "title": "مثقال طلا ",
      "dp": 1.07,
      "type": "high",
      "h": "282730000",
      "l": "279530000",
      "p": "281610000",
      "t": "۱۸:۳۹:۴۸",
      "id": 137120
    },
    {
      "title": "طلای 18 عیار / 750",
      "dp": 1.01,
      "type": "high",
      "h": "65250000",
      "l": "64326000",
      "p": "64926000",
      "t": "۱۸:۳۹:۴۷",
      "id": 137121
    },
    {
      "title": "طلای ۲۴ عیار",
      "dp": 1.01,
      "type": "high",
      "h": "86999000",
      "l": "85767000",
      "p": "86568000",
      "t": "۱۸:۳۹:۴۷",
      "id": 137122
    },
    {
      "title": "آبشده بنکداری ",
      "dp": 1.01,
      "type": "high",
      "h": "282680000",
      "l": "278680000",
      "p": "281280000",
      "t": "۱۸:۳۹:۴۶",
      "id": 137147
    },
    {
      "title": "طلای 18 عیار / 740",
      "dp": 1.01,
      "type": "high",
      "h": "64380000",
      "l": "63468000",
      "p": "64061000",
      "t": "۱۸:۳۹:۴۷",
      "id": 391292
    },
    {
      "title": "آبشده کمتر از کیلو ",
      "dp": 1.01,
      "type": "high",
      "h": "282730000",
      "l": "278730000",
      "p": "281330000",
      "t": "۱۸:۳۹:۴۷",
      "id": 391294
    },
    {
      "title": "طلای دست دوم",
      "dp": 1.01,
      "type": "high",
      "h": "64379620",
      "l": "63468470",
      "p": "64060720",
      "t": "۱۸:۳۹:۴۷",
      "id": 391295
    },
    {
      "title": "مثقال / بدون حباب",
      "dp": 0.31,
      "type": "high",
      "h": "284266000",
      "l": "282918000",
      "p": "284145000",
      "t": "۱۸:۳۹:۴۸",
      "id": 137148
    }
  ]
}