{
  "fetched_at": "2025-05-25T07:39:02.433Z",
  "data": [
    {
      "title": "طلای 18 عیار / 750",
      "dp": 0.08,
      "type": "low",
      "h": "65707000",
      "l": "65603000",
      "p": "65635000",
      "t": "۱۱:۰۵:۴۲",
      "id": 137121
    },
    {
      "title": "طلای ۲۴ عیار",
      "dp": 0.08,
      "type": "low",
      "h": "87608000",
      "l": "87470000",
      "p": "87513000",
      "t": "۱۱:۰۵:۴۲",
      "id": 137122
    },
    {
      "title": "آبشده بنکداری ",
      "dp": 0.08,
      "type": "low",
      "h": "284660000",
      "l": "284210000",
      "p": "284350000",
      "t": "۱۱:۰۵:۴۲",
      "id": 137147
    },
    {
      "title": "مثقال / بدون حباب",
      "dp": 0.08,
      "type": "low",
      "h": "290603000",
      "l": "290463000",
      "p": "290603000",
      "t": "۱۱:۰۴:۴۴",
      "id": 137148
    },
    {
      "title": "طلای 18 عیار / 740",
      "dp": 0.08,
      "type": "low",
      "h": "64831000",
      "l": "64728000",
      "p": "64760000",
      "t": "۱۱:۰۵:۴۲",
      "id": 391292
    },
    {
      "title": "آبشده کمتر از کیلو ",
      "dp": 0.08,
      "type": "low",
      "h": "284710000",
      "l": "284260000",
      "p": "284400000",
      "t": "۱۱:۰۵:۴۲",
      "id": 391294
    },
    {
      "title": "طلای دست دوم",
      "dp": 0.08,
      "type": "low",
      "h": "64830640",
      "l": "64728130",
      "p": "64760020",
      "t": "۱۱:۰۵:۴۳",
      "id": 391295
    },
    {
      "title": "مثقال طلا ",
      "dp": 0,
      "type": "",
      "h": "284710000",
      "l": "284160000",
      "p": "284610000",
      "t": "۱۱:۰۵:۵۶",
      "id": 137120
    }
  ]
}