{
  "fetched_at": "2025-05-29T10:18:42.966Z",
  "data": [
    {
      "title": "مثقال / بدون حباب",
      "dp": 0.83,
      "type": "low",
      "h": "283143000",
      "l": "281636000",
      "p": "282521000",
      "t": "۱۳:۴۵:۵۱",
      "id": 137148
    },
    {
      "title": "مثقال طلا ",
      "dp": 0.61,
      "type": "low",
      "h": "278530000",
      "l": "276410000",
      "p": "277330000",
      "t": "۱۳:۴۷:۴۹",
      "id": 137120
    },
    {
      "title": "طلای 18 عیار / 750",
      "dp": 0.61,
      "type": "low",
      "h": "64303000",
      "l": "63814000",
      "p": "64031000",
      "t": "۱۳:۴۵:۴۸",
      "id": 137121
    },
    {
      "title": "طلای ۲۴ عیار",
      "dp": 0.61,
      "type": "low",
      "h": "85737000",
      "l": "85084000",
      "p": "85373000",
      "t": "۱۳:۴۵:۴۸",
      "id": 137122
    },
    {
      "title": "آبشده بنکداری ",
      "dp": 0.61,
      "type": "low",
      "h": "278580000",
      "l": "276460000",
      "p": "277400000",
      "t": "۱۳:۴۵:۴۷",
      "id": 137147
    },
    {
      "title": "طلای 18 عیار / 740",
      "dp": 0.61,
      "type": "low",
      "h": "63446000",
      "l": "62963000",
      "p": "63177000",
      "t": "۱۳:۴۵:۴۹",
      "id": 391292
    },
    {
      "title": "آبشده کمتر از کیلو ",
      "dp": 0.61,
      "type": "low",
      "h": "278630000",
      "l": "276510000",
      "p": "277450000",
      "t": "۱۳:۴۵:۴۷",
      "id": 391294
    },
    {
      "title": "طلای دست دوم",
      "dp": 0.61,
      "type": "low",
      "h": "63445690",
      "l": "62962780",
      "p": "63176900",
      "t": "۱۳:۴۵:۵۰",
      "id": 391295
    }
  ]
}